{
  "swagger": "2.0",
  "info": {
    "title": "User API",
    "version": "1.0.0",
    "contact": {
      "name": "antoneka",
      "email": "aeho11@mail.ru"
    }
  },
  "tags": [
    {
      "name": "UserV1"
    }
  ],
  "host": "localhost:8080",
  "schemes": [
    "http",
    "https"
  ],
  "consumes": [
    "application/json"
  ],
  "produces": [
    "application/json"
  ],
  "paths": {
    "/user/v1": {
      "get": {
        "summary": "Get gets information about the user.",
        "operationId": "UserV1_Get",
        "responses": {
          "200": {
            "description": "A successful response.",
            "schema": {
              "$ref": "#/definitions/user_v1GetResponse"
            }
          },
          "default": {
            "description": "An unexpected error response.",
            "schema": {
              "$ref": "#/definitions/rpcStatus"
            }
          }
        },
        "parameters": [
          {
            "name": "id",
            "description": "ID of the user to get the information for.",
            "in": "query",
            "required": false,
            "type": "string",
            "format": "int64"
          }
        ],
        "tags": [
          "UserV1"
        ]
      },
      "delete": {
        "summary": "Delete deletes the user from the system.",
        "operationId": "UserV1_Delete",
        "responses": {
          "200": {
            "description": "A successful response.",
            "schema": {
              "type": "object",
              "properties": {}
            }
          },
          "default": {
            "description": "An unexpected error response.",
            "schema": {
              "$ref": "#/definitions/rpcStatus"
            }
          }
        },
        "parameters": [
          {
            "name": "id",
            "description": "ID of the user to be deleted from the system.",
            "in": "query",
            "required": false,
            "type": "string",
            "format": "int64"
          }
        ],
        "tags": [
          "UserV1"
        ]
      },
      "post": {
        "summary": "Create creates a new user.",
        "operationId": "UserV1_Create",
        "responses": {
          "200": {
            "description": "A successful response.",
            "schema": {
              "$ref": "#/definitions/user_v1CreateResponse"
            }
          },
          "default": {
            "description": "An unexpected error response.",
            "schema": {
              "$ref": "#/definitions/rpcStatus"
            }
          }
        },
        "parameters": [
          {
            "name": "body",
            "in": "body",
            "required": true,
            "schema": {
              "$ref": "#/definitions/user_v1CreateRequest"
            }
          }
        ],
        "tags": [
          "UserV1"
        ]
      },
      "patch": {
        "summary": "Update updates user information.",
        "operationId": "UserV1_Update",
        "responses": {
          "200": {
            "description": "A successful response.",
            "schema": {
              "type": "object",
              "properties": {}
            }
          },
          "default": {
            "description": "An unexpected error response.",
            "schema": {
              "$ref": "#/definitions/rpcStatus"
            }
          }
        },
        "parameters": [
          {
            "name": "body",
            "in": "body",
            "required": true,
            "schema": {
              "$ref": "#/definitions/user_v1UpdateRequest"
            }
          }
        ],
        "tags": [
          "UserV1"
        ]
      }
    }
  },
  "definitions": {
    "protobufAny": {
      "type": "object",
      "properties": {
        "@type": {
          "type": "string"
        }
      },
      "additionalProperties": {}
    },
    "rpcStatus": {
      "type": "object",
      "properties": {
        "code": {
          "type": "integer",
          "format": "int32"
        },
        "message": {
          "type": "string"
        },
        "details": {
          "type": "array",
          "items": {
            "type": "object",
            "$ref": "#/definitions/protobufAny"
          }
        }
      }
    },
    "user_v1CreateRequest": {
      "type": "object",
      "properties": {
        "name": {
          "type": "string",
          "description": "Name of the user to create."
        },
        "email": {
          "type": "string",
          "description": "Email of the user to create."
        },
        "password": {
          "type": "string",
          "description": "Password of the user to create."
        }
      }
    },
    "user_v1CreateResponse": {
      "type": "object",
      "properties": {
        "id": {
          "type": "string",
          "format": "int64",
          "description": "ID of the created user."
        }
      }
    },
    "user_v1GetResponse": {
      "type": "object",
      "properties": {
        "id": {
          "type": "string",
          "format": "int64",
          "description": "User ID."
        },
        "name": {
          "type": "string",
          "description": "Name of the user."
        },
        "email": {
          "type": "string",
          "description": "Email of the user."
        },
        "createdAt": {
          "type": "string",
          "format": "date-time",
          "description": "Time when the user was created."
        },
        "updatedAt": {
          "type": "string",
          "format": "date-time",
          "description": "Time when the user was last updated."
        }
      }
    },
    "user_v1UpdateRequest": {
      "type": "object",
      "properties": {
        "id": {
          "type": "string",
          "format": "int64",
          "description": "ID of the user to update the information for."
        },
        "name": {
          "type": "string",
          "description": "New name of the user."
        },
        "email": {
          "type": "string",
          "description": "New email of the user."
        },
        "password": {
          "type": "string",
          "description": "New password of the user."
        }
      }
    }
  }
}
